{
	"info": {
		"_postman_id": "531a4713-1f5c-4f32-bbf9-ed54483da028",
		"name": "PRDDRS",
		"schema": "https://schema.getpostman.com/json/collection/v2.1.0/collection.json",
		"_exporter_id": "19632023"
	},
	"item": [
		{
			"name": "Questions",
			"item": [
				{
					"name": "questions",
					"request": {
						"method": "GET",
						"header": [
							{
								"key": "Authorization",
								"value": "Bearer {{JWT}}",
								"type": "text"
							}
						],
						"url": {
							"raw": "http://localhost:8000/questions/",
							"protocol": "http",
							"host": [
								"localhost"
							],
							"port": "8000",
							"path": [
								"questions",
								""
							]
						}
					},
					"response": []
				},
				{
					"name": "questions/{type}",
					"request": {
						"method": "GET",
						"header": [
							{
								"key": "Authorization",
								"value": "Bearer {{JWT}}",
								"type": "text"
							}
						],
						"url": {
							"raw": "http://localhost:8000/questions/libre/",
							"protocol": "http",
							"host": [
								"localhost"
							],
							"port": "8000",
							"path": [
								"questions",
								"libre",
								""
							]
						}
					},
					"response": []
				},
				{
					"name": "questions/{type}/{id}",
					"request": {
						"method": "GET",
						"header": [
							{
								"key": "Authorization",
								"value": "Bearer {{JWT}}",
								"type": "text"
							}
						],
						"url": {
							"raw": "http://localhost:8000/questions/libre/1",
							"protocol": "http",
							"host": [
								"localhost"
							],
							"port": "8000",
							"path": [
								"questions",
								"libre",
								"1"
							]
						}
					},
					"response": []
				}
			]
		},
		{
			"name": "Questionnaires",
			"item": [
				{
					"name": "questionnaires",
					"request": {
						"method": "GET",
						"header": [
							{
								"key": "Authorization",
								"value": "Bearer {{JWT}}",
								"type": "text"
							}
						],
						"url": {
							"raw": "http://localhost:8000/questionnaires/",
							"protocol": "http",
							"host": [
								"localhost"
							],
							"port": "8000",
							"path": [
								"questionnaires",
								""
							]
						}
					},
					"response": []
				},
				{
					"name": "questionnaires",
					"request": {
						"method": "POST",
						"header": [
							{
								"key": "Authorization",
								"value": "Bearer {{JWT}}",
								"type": "text"
							}
						],
						"body": {
							"mode": "raw",
							"raw": "{\n    \"title_text\": \"Un super questionnaire numéro deux !\",\n    \"MONTHSTART_START\": \"1975-09-01T00:00:00.000Z\",\n    \"MONTHSTART_END\": \"1975-09-14T00:00:00.000Z\",\n    \"MONTHEND_START\": \"1975-09-15T00:00:00.000Z\",\n    \"MONTHEND_END\": \"1975-09-30T00:00:00.000Z\"\n}",
							"options": {
								"raw": {
									"language": "json"
								}
							}
						},
						"url": {
							"raw": "http://localhost:8000/questionnaires/",
							"protocol": "http",
							"host": [
								"localhost"
							],
							"port": "8000",
							"path": [
								"questionnaires",
								""
							]
						}
					},
					"response": []
				},
				{
					"name": "questionnaires/{}",
					"request": {
						"method": "GET",
						"header": [
							{
								"key": "Authorization",
								"value": "Bearer {{JWT}}",
								"type": "text"
							}
						],
						"url": {
							"raw": "http://localhost:8000/questionnaires/15/",
							"protocol": "http",
							"host": [
								"localhost"
							],
							"port": "8000",
							"path": [
								"questionnaires",
								"15",
								""
							]
						}
					},
					"response": []
				},
				{
					"name": "questionnaires/{}",
					"request": {
						"method": "DELETE",
						"header": [
							{
								"key": "Authorization",
								"value": "Bearer {{JWT}}",
								"type": "text"
							}
						],
						"url": {
							"raw": "http://localhost:8000/questionnaires/15/",
							"protocol": "http",
							"host": [
								"localhost"
							],
							"port": "8000",
							"path": [
								"questionnaires",
								"15",
								""
							]
						}
					},
					"response": []
				}
			]
		},
		{
			"name": "JWT",
			"item": [
				{
					"name": "getToken",
					"request": {
						"method": "GET",
						"header": [],
						"url": {
							"raw": "http://localhost:8000/getToken/",
							"protocol": "http",
							"host": [
								"localhost"
							],
							"port": "8000",
							"path": [
								"getToken",
								""
							]
						}
					},
					"response": []
				},
				{
					"name": "users",
					"protocolProfileBehavior": {
						"disableBodyPruning": true,
						"followRedirects": true,
						"disableUrlEncoding": false
					},
					"request": {
						"method": "GET",
						"header": [
							{
								"key": "Content-Type",
								"value": "application/json",
								"type": "text"
							},
							{
								"key": "Authorization",
								"value": "Bearer {{JWT}}",
								"type": "text"
							}
						],
						"body": {
							"mode": "urlencoded",
							"urlencoded": []
						},
						"url": {
							"raw": "http://localhost:8000/users/",
							"protocol": "http",
							"host": [
								"localhost"
							],
							"port": "8000",
							"path": [
								"users",
								""
							]
						}
					},
					"response": []
				},
				{
					"name": "users/{}",
					"request": {
						"method": "GET",
						"header": [
							{
								"key": "Content-Type",
								"value": "application/json",
								"type": "text"
							},
							{
								"key": "Authorization",
								"value": "Bearer {{JWT}}",
								"type": "text"
							},
							{
								"key": "",
								"value": "",
								"type": "text",
								"disabled": true
							}
						],
						"url": {
							"raw": "http://localhost:8000/users/1/",
							"protocol": "http",
							"host": [
								"localhost"
							],
							"port": "8000",
							"path": [
								"users",
								"1",
								""
							]
						}
					},
					"response": []
				},
				{
					"name": "admin",
					"request": {
						"method": "GET",
						"header": [
							{
								"key": "Authorization",
								"value": "Bearer {{JWT}}",
								"type": "text"
							}
						],
						"url": {
							"raw": "http://localhost:8000/admin/",
							"protocol": "http",
							"host": [
								"localhost"
							],
							"port": "8000",
							"path": [
								"admin",
								""
							]
						}
					},
					"response": []
				},
				{
					"name": "refreshToken",
					"request": {
						"method": "POST",
						"header": [
							{
								"key": "",
								"value": "",
								"type": "text",
								"disabled": true
							}
						],
						"body": {
							"mode": "raw",
							"raw": "{\n    \"refresh\" : \"{{JWT_REFRESH}}\"\n}",
							"options": {
								"raw": {
									"language": "json"
								}
							}
						},
						"url": {
							"raw": "http://localhost:8000/refreshToken/",
							"protocol": "http",
							"host": [
								"localhost"
							],
							"port": "8000",
							"path": [
								"refreshToken",
								""
							]
						}
					},
					"response": []
				}
			]
		},
		{
			"name": "Reponses",
			"item": [
				{
					"name": "reponse",
					"request": {
						"method": "GET",
						"header": [
							{
								"key": "Authorization",
								"value": "Bearer {{JWT}}",
								"type": "text"
							}
						],
						"url": {
							"raw": "http://localhost:8000/reponses/",
							"protocol": "http",
							"host": [
								"localhost"
							],
							"port": "8000",
							"path": [
								"reponses",
								""
							]
						}
					},
					"response": []
				},
				{
					"name": "reponses/libre",
					"request": {
						"method": "GET",
						"header": [
							{
								"key": "Authorization",
								"value": "Bearer {{JWT}}",
								"type": "text"
							}
						],
						"url": {
							"raw": "http://localhost:8000/reponses/libre/",
							"protocol": "http",
							"host": [
								"localhost"
							],
							"port": "8000",
							"path": [
								"reponses",
								"libre",
								""
							]
						}
					},
					"response": []
				},
				{
					"name": "reponses/qcm",
					"request": {
						"method": "GET",
						"header": [
							{
								"key": "Authorization",
								"value": "Bearer {{JWT}}",
								"type": "text"
							}
						],
						"url": {
							"raw": "http://localhost:8000/reponses/qcm",
							"protocol": "http",
							"host": [
								"localhost"
							],
							"port": "8000",
							"path": [
								"reponses",
								"qcm"
							]
						}
					},
					"response": []
				},
				{
					"name": "reponses/libre",
					"request": {
						"method": "POST",
						"header": [
							{
								"key": "Authorization",
								"value": "Bearer {{JWT}}",
								"type": "text"
							}
						],
						"body": {
							"mode": "raw",
							"raw": "{\n    \"question_id\" : 1,\n    \"answer_text\" : \"ceci est ma réponse !\"\n}",
							"options": {
								"raw": {
									"language": "json"
								}
							}
						},
						"url": {
							"raw": "http://localhost:8000/reponses/libre/",
							"protocol": "http",
							"host": [
								"localhost"
							],
							"port": "8000",
							"path": [
								"reponses",
								"libre",
								""
							]
						}
					},
					"response": []
				},
				{
					"name": "reponses/slider",
					"request": {
						"method": "POST",
						"header": [
							{
								"key": "Authorization",
								"value": "Bearer {{JWT}}",
								"type": "text"
							}
						],
						"body": {
							"mode": "raw",
							"raw": "{\n    \"question_id\" : 1,\n    \"answer_value\" : 12\n}",
							"options": {
								"raw": {
									"language": "json"
								}
							}
						},
						"url": {
							"raw": "http://localhost:8000/reponses/slider/",
							"protocol": "http",
							"host": [
								"localhost"
							],
							"port": "8000",
							"path": [
								"reponses",
								"slider",
								""
							]
						}
					},
					"response": []
				},
				{
					"name": "reponses/qcm",
					"request": {
						"method": "POST",
						"header": [
							{
								"key": "Authorization",
								"value": "Bearer {{JWT}}",
								"type": "text"
							}
						],
						"body": {
							"mode": "raw",
							"raw": "{\n    \"question_id\" : 2,\n    \"selected_fields_ids\" : [28,29]\n}",
							"options": {
								"raw": {
									"language": "json"
								}
							}
						},
						"url": {
							"raw": "http://localhost:8000/reponses/qcm/",
							"protocol": "http",
							"host": [
								"localhost"
							],
							"port": "8000",
							"path": [
								"reponses",
								"qcm",
								""
							]
						}
					},
					"response": []
				}
			]
		}
	]
}